pyinsults/insults.py
pyinsults-0.0.0.0.14.dist-info/LICENSE
pyinsults-0.0.0.0.14.dist-info/METADATA
pyinsults-0.0.0.0.14.dist-info/WHEEL
pyinsults-0.0.0.0.14.dist-info/entry_points.txt
pyinsults-0.0.0.0.14.dist-info/top_level.txt
pyinsults-0.0.0.0.14.dist-info/RECORD
