Metadata-Version: 2.1
Name: pyinsults
Version: 0.0.0.0.14
Summary: A Python module, allowing you to cuss at your users.
Home-page: https://github.com/lucassel/pyinsults
Author: Lucas Selfslagh
License: MIT
Platform: UNKNOWN
Classifier: License :: OSI Approved :: MIT License
Classifier: Programming Language :: Python :: 3
Classifier: Programming Language :: Python :: 3.7
